README.md
setup.py
Arc_api.egg-info/PKG-INFO
Arc_api.egg-info/SOURCES.txt
Arc_api.egg-info/dependency_links.txt
Arc_api.egg-info/requires.txt
Arc_api.egg-info/top_level.txt
Arcapi/__init__.py
Arcapi/api.py
Arcapi/async_api.py
Arcapi/exceptions.py
Arcapi/sync_api.py