Metadata-Version: 1.2
Name: Arc-api
Version: 1.1
Summary: An API for Arc Prober.
Home-page: https://github.com/littlebutt/Arcapi
Author: littlebutt
Author-email: luogan199686@gmail.com
License: MIT License
Platform: any
Requires-Python: >=3.7
